mysqlite3.py
mysqlite3_mod-0.0.12.dist-info/LICENSE
mysqlite3_mod-0.0.12.dist-info/METADATA
mysqlite3_mod-0.0.12.dist-info/WHEEL
mysqlite3_mod-0.0.12.dist-info/top_level.txt
mysqlite3_mod-0.0.12.dist-info/RECORD
